pysurfer-0.11.0.data/scripts/pysurfer
surfer/__init__.py
surfer/_commandline.py
surfer/cm.py
surfer/io.py
surfer/utils.py
surfer/viz.py
surfer/tests/__init__.py
surfer/tests/test_utils.py
surfer/tests/test_viz.py
pysurfer-0.11.0.dist-info/LICENSE
pysurfer-0.11.0.dist-info/METADATA
pysurfer-0.11.0.dist-info/WHEEL
pysurfer-0.11.0.dist-info/top_level.txt
pysurfer-0.11.0.dist-info/RECORD
