Metadata-Version: 2.1
Name: pysurfer
Version: 0.11.0
Summary: PySurfer: cortical surface visualization using Python.
Home-page: http://pysurfer.github.com
Maintainer: Michael Waskom
Maintainer-email: mwaskom@stanford.edu
License: BSD (3-clause)
Download-URL: https://github.com/nipy/PySurfer
Platform: any
Classifier: Intended Audience :: Science/Research
Classifier: Intended Audience :: Developers
Classifier: Programming Language :: Python :: 2.7
Classifier: Programming Language :: Python :: 3.6
Classifier: Programming Language :: Python :: 3.7
Classifier: License :: OSI Approved
Classifier: Programming Language :: Python
Classifier: Topic :: Software Development
Classifier: Topic :: Scientific/Engineering
Classifier: Operating System :: Microsoft :: Windows
Classifier: Operating System :: POSIX
Classifier: Operating System :: Unix
Classifier: Operating System :: MacOS
Requires-Python: >=3.6
Requires-Dist: matplotlib
Requires-Dist: mayavi
Requires-Dist: nibabel (>=1.2)
Requires-Dist: numpy
Requires-Dist: scipy
Provides-Extra: save_movie
Requires-Dist: imageio (>=1.5) ; extra == 'save_movie'
